MANIFEST.in
README.md
setup.py
repofish/__init__.py
repofish/database.py
repofish/github.py
repofish/nlp.py
repofish/pubmed.py
repofish/utils.py
repofish/version.py
repofish/wikipedia.py
repofish.egg-info/PKG-INFO
repofish.egg-info/SOURCES.txt
repofish.egg-info/dependency_links.txt
repofish.egg-info/not-zip-safe
repofish.egg-info/pbr.json
repofish.egg-info/requires.txt
repofish.egg-info/top_level.txt
repofish/lib/__init__.py
repofish/lib/gensim.json
repofish/lib/nilearn.json
repofish/lib/nipype.json
repofish/lib/numpy.json
repofish/lib/skimage.json
repofish/lib/sklearn.json
repofish/lib/tensorflow.json
repofish/lib/theano.json